MANIFEST.in
README.rst
requirements.txt
setup.py
freestor/__init__.py
freestor/__main__.py
freestor/cli.py
freestor/freestor.py
freestor.egg-info/PKG-INFO
freestor.egg-info/SOURCES.txt
freestor.egg-info/dependency_links.txt
freestor.egg-info/entry_points.txt
freestor.egg-info/not-zip-safe
freestor.egg-info/requires.txt
freestor.egg-info/top_level.txt