Metadata-Version: 1.1
Name: freestor
Version: 0.2
Summary: A python library to interact with FalconStor FreeStor REST API
Home-page: http://github.com/ldfsilva/freestor
Author: Leandro Silva
Author-email: ldfsilva@gmail.com
License: UNKNOWN
Keywords: freestor,requests,falconstor,ipstor
Platform: any
Classifier: Development Status :: 4 - Beta
Classifier: Environment :: Console
Classifier: Intended Audience :: Developers
Classifier: Intended Audience :: System Administrators
Classifier: Natural Language :: English
Classifier: Programming Language :: Python :: 2.6
Classifier: Programming Language :: Python :: 2.7
Classifier: Programming Language :: Python :: 3.5
Classifier: Programming Language :: Python :: 3.6
Classifier: Programming Language :: Python :: 3.7
Classifier: Topic :: System :: Systems Administration
Classifier: Topic :: Utilities
